pilot_probing/__init__.py
pilot_probing/config.py
pilot_probing/consumer.py
pilot_probing/context.py
pilot_probing/event_queue.py
pilot_probing/http_client.py
pilot_probing/models.py
pilot_probing/openai_utils.py
pilot_probing/parsers.py
pilot_probing/prompt.py
pilot_probing/tracking.py
pilot_probing/utils.py
pilot_probing/volcengine_utils.py
pilot_probing/eval/__init__.py
pilot_probing/eval/api.py
pilot_probing/eval/eval_client.py
pilot_probing/eval/models.py
pilot_probing/optimize/__init__.py
pilot_probing/optimize/models.py
pilot_probing/optimize/optimize_client.py
pilot_probing/optimize/optimize_job.py
pilot_probing-0.0.1.dist-info/METADATA
pilot_probing-0.0.1.dist-info/WHEEL
pilot_probing-0.0.1.dist-info/licenses/LICENSE.txt
pilot_probing-0.0.1.dist-info/RECORD
